Metadata-Version: 2.4
Name: sora_sdk_rpi
Version: 2025.5.2
Summary: WebRTC SFU Sora Python SDK
Home-page: https://github.com/shiguredo/sora-python-sdk
Author-email: "Shiguredo Inc." <contact+pypi@shiguredo.jp>
License-Expression: Apache-2.0
Project-URL: Source, https://github.com/shiguredo/sora-python-sdk
Project-URL: Documentation, https://sora-python-sdk.shiguredo.jp
Project-URL: Discord, https://discord.gg/shiguredo
Classifier: Programming Language :: Python :: 3 :: Only
Classifier: Programming Language :: Python :: 3.12
Classifier: Programming Language :: Python :: 3.13
Classifier: Programming Language :: Python :: 3.14
Classifier: Programming Language :: C++
Classifier: Operating System :: MacOS :: MacOS X
Classifier: Operating System :: POSIX :: Linux
Classifier: Operating System :: Microsoft :: Windows
Requires-Python: >=3.12
License-File: LICENSE
Dynamic: home-page
Dynamic: license-file
